COPYING
MANIFEST.in
README.rst
setup.py
cmsplugin_viadeo_resume/__init__.py
cmsplugin_viadeo_resume/cms_plugins.py
cmsplugin_viadeo_resume/viadeoapi.py
cmsplugin_viadeo_resume.egg-info/PKG-INFO
cmsplugin_viadeo_resume.egg-info/SOURCES.txt
cmsplugin_viadeo_resume.egg-info/dependency_links.txt
cmsplugin_viadeo_resume.egg-info/not-zip-safe
cmsplugin_viadeo_resume.egg-info/requires.txt
cmsplugin_viadeo_resume.egg-info/top_level.txt
cmsplugin_viadeo_resume/locale/fr/LC_MESSAGES/django.po
cmsplugin_viadeo_resume/templates/cmsplugin_viadeo_resume/resume.html