Metadata-Version: 1.1
Name: cmsplugin-viadeo-resume
Version: 0.4
Summary: Viadeo resume plugin for django-cms 2.2
Home-page: http://bitbucket.org/tonioo/cmsplugin-viadeo-resume
Author: Antoine Nguyen
Author-email: tonio@ngyn.org
License: BSD
Keywords: django,django-cms,viadeo,resume
Platform: UNKNOWN
Classifier: Programming Language :: Python
Classifier: Environment :: Web Environment
Classifier: Development Status :: 4 - Beta
Classifier: Intended Audience :: Developers
Classifier: License :: OSI Approved :: BSD License
Classifier: Operating System :: OS Independent
Classifier: Framework :: Django
